streamlit_cropper/__init__.py
streamlit_cropper/frontend/build/asset-manifest.json
streamlit_cropper/frontend/build/bootstrap.min.css
streamlit_cropper/frontend/build/index.html
streamlit_cropper/frontend/build/precache-manifest.916d2b96ef2893c1a9a1265806e07e7d.js
streamlit_cropper/frontend/build/service-worker.js
streamlit_cropper/frontend/build/static/css/main.1b9fbc2f.chunk.css
streamlit_cropper/frontend/build/static/css/main.1b9fbc2f.chunk.css.map
streamlit_cropper/frontend/build/static/js/2.87df79f8.chunk.js
streamlit_cropper/frontend/build/static/js/2.87df79f8.chunk.js.LICENSE.txt
streamlit_cropper/frontend/build/static/js/2.87df79f8.chunk.js.map
streamlit_cropper/frontend/build/static/js/main.5fc3e484.chunk.js
streamlit_cropper/frontend/build/static/js/main.5fc3e484.chunk.js.LICENSE.txt
streamlit_cropper/frontend/build/static/js/main.5fc3e484.chunk.js.map
streamlit_cropper/frontend/build/static/js/runtime-main.44d30fc2.js
streamlit_cropper/frontend/build/static/js/runtime-main.44d30fc2.js.map
streamlit_cropper_fix-0.4.1.dist-info/LICENSE
streamlit_cropper_fix-0.4.1.dist-info/METADATA
streamlit_cropper_fix-0.4.1.dist-info/WHEEL
streamlit_cropper_fix-0.4.1.dist-info/top_level.txt
streamlit_cropper_fix-0.4.1.dist-info/RECORD
