Metadata-Version: 2.2
Name: streamlit-cropper-fix
Version: 0.4.1
Summary: A simple image cropper for Streamlit, with fixes added
Author-email: Jia Yi <e0774928@u.nus.edu>
Project-URL: Homepage, https://github.com/ajiayi-debug/streamlit-cropper
Project-URL: Bug Tracker, https://github.com/ajiayi-debug/streamlit-cropper/issues
Classifier: Programming Language :: Python :: 3
Classifier: License :: OSI Approved :: MIT License
Classifier: Operating System :: OS Independent
Requires-Python: >=3.7
License-File: LICENSE
Requires-Dist: streamlit>=1.27.0
Requires-Dist: Pillow>=9.2.0
Requires-Dist: numpy>=1.23.5
